{
	"name": "MainMenuBackground",
	"plugin-id": "Sprite",
	"sid": 982020117110031,
	"isGlobal": false,
	"instanceVariables": [],
	"behaviorTypes": [],
	"effectTypes": [],
	"animations": {
		"items": [
			{
				"frames": [
					{
						"width": 2000,
						"height": 960,
						"originX": 0,
						"originY": 0,
						"originalSource": "",
						"exportFormat": "png",
						"exportQuality": 0.8,
						"imageSpriteId": 4820721,
						"collisionPoly": {
							"points": [
								0,
								0,
								0.5,
								0,
								0.9995,
								0,
								0.9995,
								0.5,
								0.9995,
								0.9989583333333333,
								0.5,
								0.9989583333333333,
								0,
								0.9989583333333333,
								0,
								0.5
							]
						},
						"useCollisionPoly": true,
						"duration": 1
					}
				],
				"sid": 983018751482290,
				"name": "Animation 1",
				"isLooping": false,
				"isPingPong": false,
				"repeatCount": 1,
				"repeatTo": 0,
				"speed": 5
			}
		],
		"subfolders": []
	}
}